pyskyqremote/__init__.py
pyskyqremote/const.py
pyskyqremote/const_test.py
pyskyqremote/skyq_remote.py
pyskyqremote/version.py
pyskyqremote/classes/__init__.py
pyskyqremote/classes/app.py
pyskyqremote/classes/channel.py
pyskyqremote/classes/channelepg.py
pyskyqremote/classes/device.py
pyskyqremote/classes/deviceaccess.py
pyskyqremote/classes/favourite.py
pyskyqremote/classes/media.py
pyskyqremote/classes/programme.py
pyskyqremote/classes/recordings.py
pyskyqremote/country/__init__.py
pyskyqremote-0.3.26.dist-info/LICENSE
pyskyqremote-0.3.26.dist-info/METADATA
pyskyqremote-0.3.26.dist-info/WHEEL
pyskyqremote-0.3.26.dist-info/top_level.txt
pyskyqremote-0.3.26.dist-info/RECORD
