Metadata-Version: 2.1
Name: pyskyqremote
Version: 0.3.26
Summary: Library for Sky Q Remote
Home-page: https://github.com/RogerSelwyn/skyq_remote
Author: Roger Selwyn
Author-email: roger.selwyn@nomail.com
License: MIT
Keywords: SKYQ Remote
Platform: UNKNOWN
Requires-Python: >=3.7
Requires-Dist: requests (>=2.24.0)
Requires-Dist: websocket-client (>=0.56.0)
Requires-Dist: xmltodict (>=0.12.0)
